{
  "subject": "science",
  "subjectName": "理科",
  "unitId": "late-term-fog-formation",
  "unitName": "気象",
  "category": "後期期末テスト",
  "questions": [
    {
      "id": "sci-late-fog-formation-001",
      "question": "霧が発生するための基本条件として最も適切なのはどれですか。",
      "type": "multiple",
      "choices": [
        "地表付近の空気が冷えて飽和する",
        "地表付近の空気が温まる",
        "強い風で空気が混ざる",
        "乾燥した空気が入る"
      ],
      "answer": 0,
      "explanation": "霧は地表付近の空気が冷やされ飽和すると発生します。"
    },
    {
      "id": "sci-late-fog-formation-002",
      "question": "晴れて風が弱い夜に発生しやすい霧はどれですか。",
      "type": "multiple",
      "choices": [
        "放射霧",
        "移流霧",
        "蒸気霧",
        "海霧"
      ],
      "answer": 0,
      "explanation": "晴天で地面が冷えるときに発生する霧は放射霧です。"
    },
    {
      "id": "sci-late-fog-formation-003",
      "question": "暖かく湿った空気が冷たい海面上に流れ込むと発生しやすい霧はどれですか。",
      "type": "multiple",
      "choices": [
        "移流霧",
        "放射霧",
        "氷霧",
        "蒸気霧"
      ],
      "answer": 0,
      "explanation": "暖かい空気が冷たい海面で冷やされると移流霧ができます。"
    },
    {
      "id": "sci-late-fog-formation-004",
      "question": "冷たい空気が暖かい水面を通過したときに発生する霧はどれですか。",
      "type": "multiple",
      "choices": [
        "蒸気霧",
        "放射霧",
        "移流霧",
        "巻層雲"
      ],
      "answer": 0,
      "explanation": "暖かい水面からの蒸気が冷たい空気で急に冷やされると蒸気霧が発生します。"
    },
    {
      "id": "sci-late-fog-formation-005",
      "question": "霧が濃くなると交通にどのような影響がありますか。",
      "type": "multiple",
      "choices": [
        "視程が悪くなり事故の危険が高まる",
        "視界がよくなる",
        "風が弱まるため安全",
        "全く影響しない"
      ],
      "answer": 0,
      "explanation": "霧は視界を遮り交通事故の危険が高まるため注意が必要です。"
    }
  ]
}
